{
  "openapi": "3.0.1",
  "info": {
    "title": "DIExample",
    "version": "1.0"
  },
  "paths": {
    "/api/Notification/email": {
      "post": {
        "tags": [
          "Notification"
        ],
        "requestBody": {
          "content": {
            "application/json": {
              "schema": {
                "type": "string"
              }
            },
            "text/json": {
              "schema": {
                "type": "string"
              }
            },
            "application/*+json": {
              "schema": {
                "type": "string"
              }
            }
          }
        },
        "responses": {
          "200": {
            "description": "OK"
          }
        }
      }
    },
    "/api/Notification/sms": {
      "post": {
        "tags": [
          "Notification"
        ],
        "requestBody": {
          "content": {
            "application/json": {
              "schema": {
                "type": "string"
              }
            },
            "text/json": {
              "schema": {
                "type": "string"
              }
            },
            "application/*+json": {
              "schema": {
                "type": "string"
              }
            }
          }
        },
        "responses": {
          "200": {
            "description": "OK"
          }
        }
      }
    },
    "/api/Notification": {
      "get": {
        "tags": [
          "Notification"
        ],
        "responses": {
          "200": {
            "description": "OK"
          }
        }
      }
    }
  },
  "components": { }
}